<editor><views><complex topCell="955899518"><obj id="1106117784"><label><positive/></label></obj><obj id="1903147256"><label><neutral><some><variable id="z" isThin="true"/></some></neutral></label></obj><obj id="1574493174"><label><neutral><some><variable id="y" isThin="true"/></some></neutral></label></obj><obj id="1213277084"><label><neutral><some><variable id="x" isThin="true"/></some></neutral></label></obj><cell id="1190722523"><sourcetree><seed ref="1213277084"/></sourcetree><target ref="1106117784"/><label><positive/></label></cell><cell id="73337668"><sourcetree><seed ref="1213277084"/></sourcetree><target ref="1903147256"/><label><neutral><none/></neutral></label></cell><cell id="2078056345"><sourcetree><seed ref="1213277084"/></sourcetree><target ref="1574493174"/><label><neutral><some><variable id="f" isThin="true"/></some></neutral></label></cell><cell id="1366439254"><sourcetree><seed ref="1574493174"/></sourcetree><target ref="1903147256"/><label><neutral><some><variable id="g" isThin="true"/></some></neutral></label></cell><cell id="554420960"><sourcetree><seed ref="1903147256"/></sourcetree><target ref="1106117784"/><label><negative/></label></cell><cell id="221530387"><sourcetree><graft ref="554420960"><graft ref="1366439254"><graft ref="2078056345"><leaf ref="1213277084"/></graft></graft></graft></sourcetree><target ref="1190722523"/><label><positive/></label></cell><cell id="1672054058"><sourcetree><graft ref="1366439254"><graft ref="2078056345"><leaf ref="1213277084"/></graft></graft></sourcetree><target ref="73337668"/><label><neutral><none/></neutral></label></cell><cell id="241548164"><sourcetree><graft ref="554420960"><graft ref="73337668"><leaf ref="1213277084"/></graft></graft></sourcetree><target ref="1190722523"/><label><negative/></label></cell><cell id="955899518"><sourcetree><graft ref="241548164"><graft ref="1672054058"><leaf ref="2078056345"/><leaf ref="1366439254"/></graft><leaf ref="554420960"/></graft></sourcetree><target ref="221530387"/><label><negative/></label></cell></complex><complex topCell="1768481525"><obj id="478035819"><label><positive/></label></obj><obj id="611686506"><label><neutral><some><variable id="z" isThin="true"/></some></neutral></label></obj><obj id="610888153"><label><neutral><some><variable id="y" isThin="true"/></some></neutral></label></obj><obj id="77871164"><label><neutral><some><variable id="x" isThin="true"/></some></neutral></label></obj><cell id="963112325"><sourcetree><seed ref="77871164"/></sourcetree><target ref="478035819"/><label><positive/></label></cell><cell id="1444598836"><sourcetree><seed ref="77871164"/></sourcetree><target ref="611686506"/><label><neutral><some><variable id="h" isThin="true"/></some></neutral></label></cell><cell id="2070007317"><sourcetree><seed ref="77871164"/></sourcetree><target ref="610888153"/><label><neutral><some><variable id="f" isThin="true"/></some></neutral></label></cell><cell id="1377895419"><sourcetree><seed ref="610888153"/></sourcetree><target ref="611686506"/><label><neutral><none/></neutral></label></cell><cell id="1972141532"><sourcetree><seed ref="611686506"/></sourcetree><target ref="478035819"/><label><negative/></label></cell><cell id="1520120526"><sourcetree><graft ref="1972141532"><graft ref="1377895419"><graft ref="2070007317"><leaf ref="77871164"/></graft></graft></graft></sourcetree><target ref="963112325"/><label><positive/></label></cell><cell id="52732123"><sourcetree><graft ref="1377895419"><graft ref="2070007317"><leaf ref="77871164"/></graft></graft></sourcetree><target ref="1444598836"/><label><neutral><none/></neutral></label></cell><cell id="1505528697"><sourcetree><graft ref="1972141532"><graft ref="1444598836"><leaf ref="77871164"/></graft></graft></sourcetree><target ref="963112325"/><label><negative/></label></cell><cell id="1768481525"><sourcetree><graft ref="1505528697"><graft ref="52732123"><leaf ref="2070007317"/><leaf ref="1377895419"/></graft><leaf ref="1972141532"/></graft></sourcetree><target ref="1520120526"/><label><negative/></label></cell></complex><complex topCell="1664843971"><obj id="1695316195"><label><positive/></label></obj><obj id="366260969"><label><neutral><some><variable id="w" isThin="true"/></some></neutral></label></obj><obj id="1059973681"><label><neutral><some><variable id="z" isThin="true"/></some></neutral></label></obj><obj id="1600804702"><label><neutral><some><variable id="y" isThin="true"/></some></neutral></label></obj><obj id="1049496898"><label><neutral><some><variable id="x" isThin="true"/></some></neutral></label></obj><cell id="1611171875"><sourcetree><seed ref="1049496898"/></sourcetree><target ref="1695316195"/><label><positive/></label></cell><cell id="1344398102"><sourcetree><seed ref="1049496898"/></sourcetree><target ref="366260969"/><label><neutral><some><variable id="i" isThin="true"/></some></neutral></label></cell><cell id="1623450227"><sourcetree><seed ref="1049496898"/></sourcetree><target ref="1059973681"/><label><neutral><some><variable id="h" isThin="true"/></some></neutral></label></cell><cell id="1548230054"><sourcetree><seed ref="1049496898"/></sourcetree><target ref="1600804702"/><label><neutral><some><variable id="f" isThin="true"/></some></neutral></label></cell><cell id="43166879"><sourcetree><seed ref="1600804702"/></sourcetree><target ref="1059973681"/><label><neutral><some><variable id="g" isThin="true"/></some></neutral></label></cell><cell id="1803746314"><sourcetree><seed ref="1059973681"/></sourcetree><target ref="366260969"/><label><neutral><some><variable id="k" isThin="true"/></some></neutral></label></cell><cell id="1685138346"><sourcetree><seed ref="366260969"/></sourcetree><target ref="1695316195"/><label><negative/></label></cell><cell id="1105844586"><sourcetree><graft ref="1685138346"><graft ref="1803746314"><graft ref="43166879"><graft ref="1548230054"><leaf ref="1049496898"/></graft></graft></graft></graft></sourcetree><target ref="1611171875"/><label><positive/></label></cell><cell id="1606475764"><sourcetree><graft ref="1803746314"><graft ref="43166879"><graft ref="1548230054"><leaf ref="1049496898"/></graft></graft></graft></sourcetree><target ref="1344398102"/><label><neutral><none/></neutral></label></cell><cell id="1873755464"><sourcetree><graft ref="43166879"><graft ref="1548230054"><leaf ref="1049496898"/></graft></graft></sourcetree><target ref="1623450227"/><label><neutral><some><variable id="a" isThin="true"/></some></neutral></label></cell><cell id="1507883840"><sourcetree><graft ref="1803746314"><graft ref="1623450227"><leaf ref="1049496898"/></graft></graft></sourcetree><target ref="1344398102"/><label><neutral><some><variable id="b" isThin="true"/></some></neutral></label></cell><cell id="549180633"><sourcetree><graft ref="1685138346"><graft ref="1344398102"><leaf ref="1049496898"/></graft></graft></sourcetree><target ref="1611171875"/><label><negative/></label></cell><cell id="194184025"><sourcetree><graft ref="549180633"><graft ref="1507883840"><graft ref="1873755464"><leaf ref="1548230054"/><leaf ref="43166879"/></graft><leaf ref="1803746314"/></graft><leaf ref="1685138346"/></graft></sourcetree><target ref="1105844586"/><label><positive/></label></cell><cell id="1623248382"><sourcetree><graft ref="1507883840"><graft ref="1873755464"><leaf ref="1548230054"/><leaf ref="43166879"/></graft><leaf ref="1803746314"/></graft></sourcetree><target ref="1606475764"/><label><neutral><none/></neutral></label></cell><cell id="303304786"><sourcetree><graft ref="549180633"><graft ref="1606475764"><leaf ref="1548230054"/><leaf ref="43166879"/><leaf ref="1803746314"/></graft><leaf ref="1685138346"/></graft></sourcetree><target ref="1105844586"/><label><negative/></label></cell><cell id="1664843971"><sourcetree><graft ref="303304786"><graft ref="1623248382"><leaf ref="1873755464"/><leaf ref="1507883840"/></graft><leaf ref="549180633"/></graft></sourcetree><target ref="194184025"/><label><negative/></label></cell></complex><complex topCell="1187858684"><obj id="1468183834"><label><positive/></label></obj><obj id="1178594008"><label><neutral><some><variable id="w" isThin="true"/></some></neutral></label></obj><obj id="240332528"><label><neutral><some><variable id="z" isThin="true"/></some></neutral></label></obj><obj id="1999541736"><label><neutral><some><variable id="y" isThin="true"/></some></neutral></label></obj><obj id="326365049"><label><neutral><some><variable id="x" isThin="true"/></some></neutral></label></obj><cell id="544144105"><sourcetree><seed ref="326365049"/></sourcetree><target ref="1468183834"/><label><positive/></label></cell><cell id="1444603809"><sourcetree><seed ref="326365049"/></sourcetree><target ref="1178594008"/><label><neutral><some><variable id="i" isThin="true"/></some></neutral></label></cell><cell id="6104881"><sourcetree><seed ref="326365049"/></sourcetree><target ref="240332528"/><label><neutral><some><variable id="h" isThin="true"/></some></neutral></label></cell><cell id="1673003558"><sourcetree><seed ref="326365049"/></sourcetree><target ref="1999541736"/><label><neutral><some><variable id="f" isThin="true"/></some></neutral></label></cell><cell id="1167409135"><sourcetree><seed ref="1999541736"/></sourcetree><target ref="240332528"/><label><neutral><some><variable id="g" isThin="true"/></some></neutral></label></cell><cell id="1234732953"><sourcetree><seed ref="240332528"/></sourcetree><target ref="1178594008"/><label><neutral><some><variable id="k" isThin="true"/></some></neutral></label></cell><cell id="1022260110"><sourcetree><seed ref="1178594008"/></sourcetree><target ref="1468183834"/><label><negative/></label></cell><cell id="1256492770"><sourcetree><graft ref="1022260110"><graft ref="1234732953"><graft ref="1167409135"><graft ref="1673003558"><leaf ref="326365049"/></graft></graft></graft></graft></sourcetree><target ref="544144105"/><label><positive/></label></cell><cell id="1667284439"><sourcetree><graft ref="1234732953"><graft ref="1167409135"><graft ref="1673003558"><leaf ref="326365049"/></graft></graft></graft></sourcetree><target ref="1444603809"/><label><neutral><some><variable id="c" isThin="true"/></some></neutral></label></cell><cell id="1682940217"><sourcetree><graft ref="1167409135"><graft ref="1673003558"><leaf ref="326365049"/></graft></graft></sourcetree><target ref="6104881"/><label><neutral><some><variable id="a" isThin="true"/></some></neutral></label></cell><cell id="669112482"><sourcetree><graft ref="1234732953"><graft ref="6104881"><leaf ref="326365049"/></graft></graft></sourcetree><target ref="1444603809"/><label><neutral><none/></neutral></label></cell><cell id="1549109282"><sourcetree><graft ref="1022260110"><graft ref="1444603809"><leaf ref="326365049"/></graft></graft></sourcetree><target ref="544144105"/><label><negative/></label></cell><cell id="1935449993"><sourcetree><graft ref="1549109282"><graft ref="669112482"><graft ref="1682940217"><leaf ref="1673003558"/><leaf ref="1167409135"/></graft><leaf ref="1234732953"/></graft><leaf ref="1022260110"/></graft></sourcetree><target ref="1256492770"/><label><positive/></label></cell><cell id="1173231242"><sourcetree><graft ref="669112482"><graft ref="1682940217"><leaf ref="1673003558"/><leaf ref="1167409135"/></graft><leaf ref="1234732953"/></graft></sourcetree><target ref="1667284439"/><label><neutral><none/></neutral></label></cell><cell id="302637540"><sourcetree><graft ref="1549109282"><graft ref="1667284439"><leaf ref="1673003558"/><leaf ref="1167409135"/><leaf ref="1234732953"/></graft><leaf ref="1022260110"/></graft></sourcetree><target ref="1256492770"/><label><negative/></label></cell><cell id="1187858684"><sourcetree><graft ref="302637540"><graft ref="1173231242"><leaf ref="1682940217"/><leaf ref="669112482"/></graft><leaf ref="1549109282"/></graft></sourcetree><target ref="1935449993"/><label><negative/></label></cell></complex><complex topCell="1553129907"><obj id="1332919476"><label><positive/></label></obj><obj id="1975711275"><label><neutral><some><variable id="w" isThin="true"/></some></neutral></label></obj><obj id="1387249011"><label><neutral><some><variable id="z" isThin="true"/></some></neutral></label></obj><obj id="264172398"><label><neutral><some><variable id="y" isThin="true"/></some></neutral></label></obj><obj id="1096794837"><label><neutral><some><variable id="x" isThin="true"/></some></neutral></label></obj><cell id="1978683258"><sourcetree><seed ref="1096794837"/></sourcetree><target ref="1332919476"/><label><positive/></label></cell><cell id="1945243411"><sourcetree><seed ref="1096794837"/></sourcetree><target ref="1975711275"/><label><neutral><some><variable id="j" isThin="true"/></some></neutral></label></cell><cell id="414966749"><sourcetree><seed ref="1096794837"/></sourcetree><target ref="1975711275"/><label><neutral><some><variable id="i" isThin="true"/></some></neutral></label></cell><cell id="1466748634"><sourcetree><seed ref="1096794837"/></sourcetree><target ref="1387249011"/><label><neutral><some><variable id="h" isThin="true"/></some></neutral></label></cell><cell id="679507725"><sourcetree><seed ref="1096794837"/></sourcetree><target ref="264172398"/><label><neutral><some><variable id="f" isThin="true"/></some></neutral></label></cell><cell id="168299329"><sourcetree><seed ref="264172398"/></sourcetree><target ref="1387249011"/><label><neutral><some><variable id="g" isThin="true"/></some></neutral></label></cell><cell id="370859404"><sourcetree><seed ref="1387249011"/></sourcetree><target ref="1975711275"/><label><neutral><some><variable id="k" isThin="true"/></some></neutral></label></cell><cell id="1036459434"><sourcetree><seed ref="1975711275"/></sourcetree><target ref="1332919476"/><label><negative/></label></cell><cell id="1533846421"><sourcetree><graft ref="1036459434"><graft ref="370859404"><graft ref="168299329"><graft ref="679507725"><leaf ref="1096794837"/></graft></graft></graft></graft></sourcetree><target ref="1978683258"/><label><positive/></label></cell><cell id="963099159"><sourcetree><graft ref="370859404"><graft ref="168299329"><graft ref="679507725"><leaf ref="1096794837"/></graft></graft></graft></sourcetree><target ref="1945243411"/><label><neutral><some><variable id="s" isThin="true"/></some></neutral></label></cell><cell id="1223317874"><sourcetree><graft ref="370859404"><graft ref="168299329"><graft ref="679507725"><leaf ref="1096794837"/></graft></graft></graft></sourcetree><target ref="414966749"/><label><neutral><some><variable id="c" isThin="true"/></some></neutral></label></cell><cell id="295071940"><sourcetree><graft ref="168299329"><graft ref="679507725"><leaf ref="1096794837"/></graft></graft></sourcetree><target ref="1466748634"/><label><neutral><some><variable id="a" isThin="true"/></some></neutral></label></cell><cell id="734354657"><sourcetree><graft ref="370859404"><graft ref="1466748634"><leaf ref="1096794837"/></graft></graft></sourcetree><target ref="414966749"/><label><neutral><some><variable id="b" isThin="true"/></some></neutral></label></cell><cell id="710200890"><sourcetree><graft ref="414966749"><leaf ref="1096794837"/></graft></sourcetree><target ref="414966749"/><label><neutral><some><variable id="d" isThin="true"/></some></neutral></label></cell><cell id="632248204"><sourcetree><graft ref="414966749"><leaf ref="1096794837"/></graft></sourcetree><target ref="1945243411"/><label><neutral><some><variable id="e" isThin="true"/></some></neutral></label></cell><cell id="446479272"><sourcetree><graft ref="1036459434"><graft ref="1945243411"><leaf ref="1096794837"/></graft></graft></sourcetree><target ref="1978683258"/><label><negative/></label></cell><cell id="669261886"><sourcetree><graft ref="446479272"><graft ref="632248204"><graft ref="734354657"><graft ref="295071940"><leaf ref="679507725"/><leaf ref="168299329"/></graft><leaf ref="370859404"/></graft></graft><leaf ref="1036459434"/></graft></sourcetree><target ref="1533846421"/><label><positive/></label></cell><cell id="1912658663"><sourcetree><graft ref="632248204"><graft ref="734354657"><graft ref="295071940"><leaf ref="679507725"/><leaf ref="168299329"/></graft><leaf ref="370859404"/></graft></graft></sourcetree><target ref="963099159"/><label><neutral><some><variable id="v" isThin="true"/></some></neutral></label></cell><cell id="371437098"><sourcetree><graft ref="734354657"><graft ref="295071940"><leaf ref="679507725"/><leaf ref="168299329"/></graft><leaf ref="370859404"/></graft></sourcetree><target ref="1223317874"/><label><neutral><some><variable id="u" isThin="true"/></some></neutral></label></cell><cell id="8344257"><sourcetree><leaf ref="414966749"/></sourcetree><target ref="710200890"/><label><neutral><none/></neutral></label></cell><cell id="655490344"><sourcetree><graft ref="632248204"><graft ref="710200890"><graft ref="1223317874"><leaf ref="679507725"/><leaf ref="168299329"/><leaf ref="370859404"/></graft></graft></graft></sourcetree><target ref="963099159"/><label><neutral><some><variable id="t" isThin="true"/></some></neutral></label></cell><cell id="235102498"><sourcetree><graft ref="446479272"><graft ref="963099159"><leaf ref="679507725"/><leaf ref="168299329"/><leaf ref="370859404"/></graft><leaf ref="1036459434"/></graft></sourcetree><target ref="1533846421"/><label><negative/></label></cell><cell id="2145257053"><sourcetree><graft ref="235102498"><graft ref="655490344"><graft ref="371437098"><leaf ref="295071940"/><leaf ref="734354657"/></graft><graft ref="8344257"></graft><leaf ref="632248204"/></graft><leaf ref="446479272"/></graft></sourcetree><target ref="669261886"/><label><positive/></label></cell><cell id="1232340288"><sourcetree><graft ref="655490344"><graft ref="371437098"><leaf ref="295071940"/><leaf ref="734354657"/></graft><graft ref="8344257"></graft><leaf ref="632248204"/></graft></sourcetree><target ref="1912658663"/><label><neutral><none/></neutral></label></cell><cell id="1610928748"><sourcetree><graft ref="235102498"><graft ref="1912658663"><leaf ref="295071940"/><leaf ref="734354657"/><leaf ref="632248204"/></graft><leaf ref="446479272"/></graft></sourcetree><target ref="669261886"/><label><negative/></label></cell><cell id="1553129907"><sourcetree><graft ref="1610928748"><graft ref="1232340288"><leaf ref="371437098"/><leaf ref="8344257"/><leaf ref="655490344"/></graft><leaf ref="235102498"/></graft></sourcetree><target ref="2145257053"/><label><negative/></label></cell></complex></views><environment><complex topCell="790617664"><obj id="790617664"><label><variable id="x" isThin="true"/></label></obj></complex><complex topCell="1429754859"><obj id="1429754859"><label><variable id="y" isThin="true"/></label></obj></complex><complex topCell="1695388930"><obj id="1695388930"><label><variable id="z" isThin="true"/></label></obj></complex><complex topCell="1500108884"><obj id="1588718114"><label><variable id="y" isThin="true"/></label></obj><obj id="1921158847"><label><variable id="x" isThin="true"/></label></obj><cell id="1500108884"><sourcetree><seed ref="1921158847"/></sourcetree><target ref="1588718114"/><label><variable id="f" isThin="true"/></label></cell></complex><complex topCell="1336704900"><obj id="871997608"><label><variable id="z" isThin="true"/></label></obj><obj id="1235390528"><label><variable id="y" isThin="true"/></label></obj><cell id="1336704900"><sourcetree><seed ref="1235390528"/></sourcetree><target ref="871997608"/><label><variable id="g" isThin="true"/></label></cell></complex><complex topCell="1383365308"><obj id="1172823033"><label><variable id="z" isThin="true"/></label></obj><obj id="2031803465"><label><variable id="x" isThin="true"/></label></obj><cell id="1383365308"><sourcetree><seed ref="2031803465"/></sourcetree><target ref="1172823033"/><label><variable id="h" isThin="true"/></label></cell></complex><complex topCell="1562769134"><obj id="1562769134"><label><variable id="w" isThin="true"/></label></obj></complex><complex topCell="26893057"><obj id="1735832328"><label><variable id="w" isThin="true"/></label></obj><obj id="568592201"><label><variable id="z" isThin="true"/></label></obj><cell id="26893057"><sourcetree><seed ref="568592201"/></sourcetree><target ref="1735832328"/><label><variable id="k" isThin="true"/></label></cell></complex><complex topCell="2145968369"><obj id="1020043129"><label><variable id="w" isThin="true"/></label></obj><obj id="502915102"><label><variable id="x" isThin="true"/></label></obj><cell id="2145968369"><sourcetree><seed ref="502915102"/></sourcetree><target ref="1020043129"/><label><variable id="i" isThin="true"/></label></cell></complex><complex topCell="704442810"><obj id="302526418"><label><variable id="z" isThin="true"/></label></obj><obj id="1467714877"><label><variable id="y" isThin="true"/></label></obj><obj id="1886768297"><label><variable id="x" isThin="true"/></label></obj><cell id="1171236077"><sourcetree><seed ref="1886768297"/></sourcetree><target ref="302526418"/><label><variable id="h" isThin="true"/></label></cell><cell id="1129637737"><sourcetree><seed ref="1886768297"/></sourcetree><target ref="1467714877"/><label><variable id="f" isThin="true"/></label></cell><cell id="2066006279"><sourcetree><seed ref="1467714877"/></sourcetree><target ref="302526418"/><label><variable id="g" isThin="true"/></label></cell><cell id="704442810"><sourcetree><graft ref="2066006279"><graft ref="1129637737"><leaf ref="1886768297"/></graft></graft></sourcetree><target ref="1171236077"/><label><variable id="a" isThin="true"/></label></cell></complex><complex topCell="1377619713"><obj id="492961759"><label><variable id="w" isThin="true"/></label></obj><obj id="216373387"><label><variable id="z" isThin="true"/></label></obj><obj id="897700938"><label><variable id="x" isThin="true"/></label></obj><cell id="1587044791"><sourcetree><seed ref="897700938"/></sourcetree><target ref="492961759"/><label><variable id="i" isThin="true"/></label></cell><cell id="1714906597"><sourcetree><seed ref="897700938"/></sourcetree><target ref="216373387"/><label><variable id="h" isThin="true"/></label></cell><cell id="1057149392"><sourcetree><seed ref="216373387"/></sourcetree><target ref="492961759"/><label><variable id="k" isThin="true"/></label></cell><cell id="1377619713"><sourcetree><graft ref="1057149392"><graft ref="1714906597"><leaf ref="897700938"/></graft></graft></sourcetree><target ref="1587044791"/><label><variable id="b" isThin="true"/></label></cell></complex><complex topCell="1397078106"><obj id="1633318084"><label><variable id="w" isThin="true"/></label></obj><obj id="2041061834"><label><variable id="z" isThin="true"/></label></obj><obj id="222466860"><label><variable id="y" isThin="true"/></label></obj><obj id="231486593"><label><variable id="x" isThin="true"/></label></obj><cell id="1502283834"><sourcetree><seed ref="231486593"/></sourcetree><target ref="1633318084"/><label><variable id="i" isThin="true"/></label></cell><cell id="919160259"><sourcetree><seed ref="231486593"/></sourcetree><target ref="222466860"/><label><variable id="f" isThin="true"/></label></cell><cell id="1476600142"><sourcetree><seed ref="222466860"/></sourcetree><target ref="2041061834"/><label><variable id="g" isThin="true"/></label></cell><cell id="897561862"><sourcetree><seed ref="2041061834"/></sourcetree><target ref="1633318084"/><label><variable id="k" isThin="true"/></label></cell><cell id="1397078106"><sourcetree><graft ref="897561862"><graft ref="1476600142"><graft ref="919160259"><leaf ref="231486593"/></graft></graft></graft></sourcetree><target ref="1502283834"/><label><variable id="c" isThin="true"/></label></cell></complex><complex topCell="892830894"><obj id="105531244"><label><variable id="w" isThin="true"/></label></obj><obj id="1989609133"><label><variable id="x" isThin="true"/></label></obj><cell id="892830894"><sourcetree><seed ref="1989609133"/></sourcetree><target ref="105531244"/><label><variable id="j" isThin="true"/></label></cell></complex><complex topCell="1873931364"><obj id="1340593869"><label><variable id="w" isThin="true"/></label></obj><obj id="2110215606"><label><variable id="x" isThin="true"/></label></obj><cell id="701259837"><sourcetree><seed ref="2110215606"/></sourcetree><target ref="1340593869"/><label><variable id="i" isThin="true"/></label></cell><cell id="683825723"><sourcetree><seed ref="2110215606"/></sourcetree><target ref="1340593869"/><label><variable id="i" isThin="true"/></label></cell><cell id="1873931364"><sourcetree><graft ref="683825723"><leaf ref="2110215606"/></graft></sourcetree><target ref="701259837"/><label><variable id="d" isThin="true"/></label></cell></complex><complex topCell="1929080475"><obj id="169267846"><label><variable id="w" isThin="true"/></label></obj><obj id="1616339094"><label><variable id="x" isThin="true"/></label></obj><cell id="143018308"><sourcetree><seed ref="1616339094"/></sourcetree><target ref="169267846"/><label><variable id="j" isThin="true"/></label></cell><cell id="674501563"><sourcetree><seed ref="1616339094"/></sourcetree><target ref="169267846"/><label><variable id="i" isThin="true"/></label></cell><cell id="1929080475"><sourcetree><graft ref="674501563"><leaf ref="1616339094"/></graft></sourcetree><target ref="143018308"/><label><variable id="e" isThin="true"/></label></cell></complex><complex topCell="854844149"><obj id="359501723"><label><variable id="w" isThin="true"/></label></obj><obj id="1273959450"><label><variable id="z" isThin="true"/></label></obj><obj id="1024515560"><label><variable id="y" isThin="true"/></label></obj><obj id="509135274"><label><variable id="x" isThin="true"/></label></obj><cell id="1461700470"><sourcetree><seed ref="509135274"/></sourcetree><target ref="359501723"/><label><variable id="j" isThin="true"/></label></cell><cell id="1734361257"><sourcetree><seed ref="509135274"/></sourcetree><target ref="1024515560"/><label><variable id="f" isThin="true"/></label></cell><cell id="1614105668"><sourcetree><seed ref="1024515560"/></sourcetree><target ref="1273959450"/><label><variable id="g" isThin="true"/></label></cell><cell id="1260533172"><sourcetree><seed ref="1273959450"/></sourcetree><target ref="359501723"/><label><variable id="k" isThin="true"/></label></cell><cell id="854844149"><sourcetree><graft ref="1260533172"><graft ref="1614105668"><graft ref="1734361257"><leaf ref="509135274"/></graft></graft></graft></sourcetree><target ref="1461700470"/><label><variable id="s" isThin="true"/></label></cell></complex><complex topCell="1962339908"><obj id="700013813"><label><variable id="w" isThin="true"/></label></obj><obj id="1216736825"><label><variable id="z" isThin="true"/></label></obj><obj id="1356531041"><label><variable id="y" isThin="true"/></label></obj><obj id="1530809535"><label><variable id="x" isThin="true"/></label></obj><cell id="1461763685"><sourcetree><seed ref="1530809535"/></sourcetree><target ref="700013813"/><label><variable id="j" isThin="true"/></label></cell><cell id="649332115"><sourcetree><seed ref="1530809535"/></sourcetree><target ref="700013813"/><label><variable id="i" isThin="true"/></label></cell><cell id="1960446398"><sourcetree><seed ref="1530809535"/></sourcetree><target ref="700013813"/><label><variable id="i" isThin="true"/></label></cell><cell id="381015265"><sourcetree><seed ref="1530809535"/></sourcetree><target ref="1356531041"/><label><variable id="f" isThin="true"/></label></cell><cell id="2074807148"><sourcetree><seed ref="1356531041"/></sourcetree><target ref="1216736825"/><label><variable id="g" isThin="true"/></label></cell><cell id="444276450"><sourcetree><seed ref="1216736825"/></sourcetree><target ref="700013813"/><label><variable id="k" isThin="true"/></label></cell><cell id="153654531"><sourcetree><graft ref="444276450"><graft ref="2074807148"><graft ref="381015265"><leaf ref="1530809535"/></graft></graft></graft></sourcetree><target ref="1461763685"/><label><variable id="s" isThin="true"/></label></cell><cell id="1196358823"><sourcetree><graft ref="444276450"><graft ref="2074807148"><graft ref="381015265"><leaf ref="1530809535"/></graft></graft></graft></sourcetree><target ref="1960446398"/><label><variable id="c" isThin="true"/></label></cell><cell id="313351300"><sourcetree><graft ref="1960446398"><leaf ref="1530809535"/></graft></sourcetree><target ref="649332115"/><label><variable id="d" isThin="true"/></label></cell><cell id="865396656"><sourcetree><graft ref="649332115"><leaf ref="1530809535"/></graft></sourcetree><target ref="1461763685"/><label><variable id="e" isThin="true"/></label></cell><cell id="1962339908"><sourcetree><graft ref="865396656"><graft ref="313351300"><graft ref="1196358823"><leaf ref="381015265"/><leaf ref="2074807148"/><leaf ref="444276450"/></graft></graft></graft></sourcetree><target ref="153654531"/><label><variable id="t" isThin="true"/></label></cell></complex><complex topCell="1806737116"><obj id="2140466777"><label><variable id="w" isThin="true"/></label></obj><obj id="179066495"><label><variable id="z" isThin="true"/></label></obj><obj id="945992018"><label><variable id="y" isThin="true"/></label></obj><obj id="1466407785"><label><variable id="x" isThin="true"/></label></obj><cell id="1393309523"><sourcetree><seed ref="1466407785"/></sourcetree><target ref="2140466777"/><label><variable id="i" isThin="true"/></label></cell><cell id="1191466173"><sourcetree><seed ref="1466407785"/></sourcetree><target ref="179066495"/><label><variable id="h" isThin="true"/></label></cell><cell id="1834444983"><sourcetree><seed ref="1466407785"/></sourcetree><target ref="945992018"/><label><variable id="f" isThin="true"/></label></cell><cell id="94109302"><sourcetree><seed ref="945992018"/></sourcetree><target ref="179066495"/><label><variable id="g" isThin="true"/></label></cell><cell id="1147074522"><sourcetree><seed ref="179066495"/></sourcetree><target ref="2140466777"/><label><variable id="k" isThin="true"/></label></cell><cell id="920792135"><sourcetree><graft ref="1147074522"><graft ref="94109302"><graft ref="1834444983"><leaf ref="1466407785"/></graft></graft></graft></sourcetree><target ref="1393309523"/><label><variable id="c" isThin="true"/></label></cell><cell id="986252663"><sourcetree><graft ref="94109302"><graft ref="1834444983"><leaf ref="1466407785"/></graft></graft></sourcetree><target ref="1191466173"/><label><variable id="a" isThin="true"/></label></cell><cell id="1669719495"><sourcetree><graft ref="1147074522"><graft ref="1191466173"><leaf ref="1466407785"/></graft></graft></sourcetree><target ref="1393309523"/><label><variable id="b" isThin="true"/></label></cell><cell id="1806737116"><sourcetree><graft ref="1669719495"><graft ref="986252663"><leaf ref="1834444983"/><leaf ref="94109302"/></graft><leaf ref="1147074522"/></graft></sourcetree><target ref="920792135"/><label><variable id="u" isThin="true"/></label></cell></complex><complex topCell="680730852"><obj id="411940032"><label><variable id="w" isThin="true"/></label></obj><obj id="2136323543"><label><variable id="z" isThin="true"/></label></obj><obj id="1410693008"><label><variable id="y" isThin="true"/></label></obj><obj id="1297922576"><label><variable id="x" isThin="true"/></label></obj><cell id="45848606"><sourcetree><seed ref="1297922576"/></sourcetree><target ref="411940032"/><label><variable id="j" isThin="true"/></label></cell><cell id="1778375416"><sourcetree><seed ref="1297922576"/></sourcetree><target ref="411940032"/><label><variable id="i" isThin="true"/></label></cell><cell id="478217766"><sourcetree><seed ref="1297922576"/></sourcetree><target ref="2136323543"/><label><variable id="h" isThin="true"/></label></cell><cell id="1522186088"><sourcetree><seed ref="1297922576"/></sourcetree><target ref="1410693008"/><label><variable id="f" isThin="true"/></label></cell><cell id="408894305"><sourcetree><seed ref="1410693008"/></sourcetree><target ref="2136323543"/><label><variable id="g" isThin="true"/></label></cell><cell id="338913735"><sourcetree><seed ref="2136323543"/></sourcetree><target ref="411940032"/><label><variable id="k" isThin="true"/></label></cell><cell id="996512301"><sourcetree><graft ref="338913735"><graft ref="408894305"><graft ref="1522186088"><leaf ref="1297922576"/></graft></graft></graft></sourcetree><target ref="45848606"/><label><variable id="s" isThin="true"/></label></cell><cell id="157279954"><sourcetree><graft ref="408894305"><graft ref="1522186088"><leaf ref="1297922576"/></graft></graft></sourcetree><target ref="478217766"/><label><variable id="a" isThin="true"/></label></cell><cell id="1999301068"><sourcetree><graft ref="338913735"><graft ref="478217766"><leaf ref="1297922576"/></graft></graft></sourcetree><target ref="1778375416"/><label><variable id="b" isThin="true"/></label></cell><cell id="576425267"><sourcetree><graft ref="1778375416"><leaf ref="1297922576"/></graft></sourcetree><target ref="45848606"/><label><variable id="e" isThin="true"/></label></cell><cell id="680730852"><sourcetree><graft ref="576425267"><graft ref="1999301068"><graft ref="157279954"><leaf ref="1522186088"/><leaf ref="408894305"/></graft><leaf ref="338913735"/></graft></graft></sourcetree><target ref="996512301"/><label><variable id="v" isThin="true"/></label></cell></complex></environment></editor>